{
    "source": "NOAA/NCEP Central Operations",
    "product": "ProbSevere",
    "validTime": "20211017_150631 UTC",
    "productionTime": "20211017_150748 UTC",
    "machine": "vm-cprk-mrms-ops-probsvr1.ncep.noaa.gov",
    "type": "FeatureCollection",
    "features": [
        {
            "type": "Feature",
            "geometry": {
                "type": "Polygon",
                "coordinates": [
                    [
                        [
                            -82.24,
                            26.53
                        ],
                        [
                            -82.22,
                            26.53
                        ],
                        [
                            -82.21,
                            26.52
                        ],
                        [
                            -82.21,
                            26.48
                        ],
                        [
                            -82.23,
                            26.45
                        ],
                        [
                            -82.26,
                            26.44
                        ],
                        [
                            -82.29,
                            26.46
                        ],
                        [
                            -82.29,
                            26.5
                        ],
                        [
                            -82.28,
                            26.5
                        ],
                        [
                            -82.24,
                            26.53
                        ]
                    ]
                ]
            },
            "models": {
                "probsevere": {
                    "PROB": "1",
                    "LINE01": "ProbHail: 0%; ProbWind: 1%; ProbTor: 0%",
                    "LINE02": "- MESH: 0.06 in.",
                    "LINE03": "- VIL Density: 0.96 g/m^3",
                    "LINE04": "- Flash Rate: 0 fl/min",
                    "LINE05": "- Flash Density (max in last 30 min): 0.02 fl/min/km^2",
                    "LINE06": "- Max LLAzShear: 0.005 /s",
                    "LINE07": "- 98% LLAzShear: 0.005 /s",
                    "LINE08": "- 98% MLAzShear: 0.005 /s",
                    "LINE09": "- Norm. vert. growth rate: 1431Z 3.6%/min (strong)",
                    "LINE10": "- EBShear: 21.9 kts; SRH 0-1km AGL: 26 m^2/s^2",
                    "LINE11": "- MUCAPE: 2191 J/kg; MLCAPE: 1714 J/kg; MLCIN: -1 J/kg",
                    "LINE12": "- MeanWind 1-3kmAGL: 6.9 kts",
                    "LINE13": "- Wetbulb 0C hgt: 12.4 kft AGL",
                    "LINE14": "- CAPE -10C to -30C: 488 J/kg; PWAT: 1.7 in.",
                    "LINE15": "Avg. beam height (ARL): 6.32 kft / 1.93 km"
                },
                "probtor": {
                    "PROB": "0",
                    "LINE01": "ProbTor: 0%",
                    "LINE02": "- Max LLAzShear: 0.005 /s (weak)",
                    "LINE03": "- 98% LLAzShear: 0.005 /s (weak)",
                    "LINE04": "- 98% MLAzShear: 0.005 /s (weak)",
                    "LINE05": "- Flash Density: 0.02 fl/min/km^2",
                    "LINE06": "- SRH 0-1km AGL: 26 m2/s2",
                    "LINE07": "- EBShear: 21.9 kts",
                    "LINE08": "- MeanWind 1-3kmAGL: 6.9 kts",
                    "LINE09": "- MLCAPE/MLCIN: 1714/-1 J/kg",
                    "LINE10": "Avg. beam height (ARL): 6.32 kft / 1.93 km"
                },
                "probhail": {
                    "PROB": "0",
                    "LINE01": "ProbHail: 0%",
                    "LINE02": "- MESH: 0.06 in.",
                    "LINE03": "- Flash Rate: 0 fl/min",
                    "LINE04": "- Norm. vert. growth rate: 1431Z 3.6%/min (strong)",
                    "LINE05": "- EBShear: 21.9 kts",
                    "LINE06": "- CAPE -10C to -30C: 488 J/kg",
                    "LINE07": "- PWAT: 1.7 in.",
                    "LINE08": "- Wetbulb 0C hgt: 12.4 kft AGL"
                },
                "probwind": {
                    "PROB": "1",
                    "LINE01": "ProbWind: 1%",
                    "LINE02": "- MESH: 0.06 in.",
                    "LINE03": "- VIL Density: 0.96 g/m^3",
                    "LINE04": "- Flash Rate: 0 fl/min",
                    "LINE05": "- 98% LLAzShear: 0.005 /s (moderate)",
                    "LINE06": "- 98% MLAzShear: 0.005 /s (moderate)",
                    "LINE07": "- Norm. vert. growth rate: 1431Z 3.6%/min (strong)",
                    "LINE08": "- EBShear: 21.9 kts",
                    "LINE09": "- MeanWind 1-3kmAGL: 6.9 kts",
                    "LINE10": "- MUCAPE: 2191 J/kg; MLCAPE: 1714 J/kg"
                }
            },
            "properties": {
                "MUCAPE": "2191",
                "MLCAPE": "1714",
                "MLCIN": "-1",
                "EBSHEAR": "21.9",
                "SRH01KM": "26",
                "MEANWIND_1-3kmAGL": "6.9",
                "MESH": "0.06",
                "VIL_DENSITY": "0.96",
                "FLASH_RATE": "0",
                "FLASH_DENSITY": "0.02",
                "MAXLLAZ": "0.005",
                "P98LLAZ": "0.005",
                "P98MLAZ": "0.005",
                "MAXRC_EMISS": "1431Z 3.6%/min (strong)",
                "MAXRC_ICECF": "1426Z 0.06/min (moderate)",
                "WETBULB_0C_HGT": "12.4",
                "PWAT": "1.7",
                "CAPE_M10M30": "488",
                "LJA": "0.0",
                "SIZE": "67",
                "AVG_BEAM_HGT": "6.32 kft / 1.93 km",
                "MOTION_EAST": "0.895",
                "MOTION_SOUTH": "-9.521",
                "PS": "2",
                "ID": "128636"
            }
        },
        {
            "type": "Feature",
            "geometry": {
                "type": "Polygon",
                "coordinates": [
                    [
                        [
                            -101.35,
                            36.54
                        ],
                        [
                            -101.33,
                            36.54
                        ],
                        [
                            -101.33,
                            36.52
                        ],
                        [
                            -101.34,
                            36.51
                        ],
                        [
                            -101.32,
                            36.49
                        ],
                        [
                            -101.32,
                            36.46
                        ],
                        [
                            -101.33,
                            36.45
                        ],
                        [
                            -101.33,
                            36.42
                        ],
                        [
                            -101.34,
                            36.41
                        ],
                        [
                            -101.37,
                            36.41
                        ],
                        [
                            -101.41,
                            36.45
                        ],
                        [
                            -101.41,
                            36.5
                        ],
                        [
                            -101.39,
                            36.52
                        ],
                        [
                            -101.39,
                            36.53
                        ],
                        [
                            -101.36,
                            36.53
                        ],
                        [
                            -101.35,
                            36.54
                        ]
                    ]
                ]
            },
            "models": {
                "probsevere": {
                    "PROB": "1",
                    "LINE01": "ProbHail: 0%; ProbWind: 1%; ProbTor: 0%",
                    "LINE02": "- MESH: 1.03 in. (flagged)",
                    "LINE03": "- VIL Density: 2.54 g/m^3",
                    "LINE04": "- Flash Rate: 0 fl/min",
                    "LINE05": "- Flash Density (max in last 30 min): 0.00 fl/min/km^2",
                    "LINE06": "- Max LLAzShear: 0.001 /s",
                    "LINE07": "- 98% LLAzShear: 0.001 /s",
                    "LINE08": "- 98% MLAzShear: 0.001 /s",
                    "LINE09": "- Norm. vert. growth rate: N/A",
                    "LINE10": "- EBShear: 0.0 kts; SRH 0-1km AGL: 22 m^2/s^2",
                    "LINE11": "- MUCAPE: 0 J/kg; MLCAPE: 0 J/kg; MLCIN: -999 J/kg",
                    "LINE12": "- MeanWind 1-3kmAGL: 13.7 kts",
                    "LINE13": "- Wetbulb 0C hgt: 6.4 kft AGL",
                    "LINE14": "- CAPE -10C to -30C: 0 J/kg; PWAT: 0.3 in.",
                    "LINE15": "Avg. beam height (ARL): 6.77 kft / 2.06 km"
                },
                "probtor": {
                    "PROB": "0",
                    "LINE01": "ProbTor: 0%",
                    "LINE02": "- Max LLAzShear: 0.001 /s (weak)",
                    "LINE03": "- 98% LLAzShear: 0.001 /s (weak)",
                    "LINE04": "- 98% MLAzShear: 0.001 /s (weak)",
                    "LINE05": "- Flash Density: 0.00 fl/min/km^2",
                    "LINE06": "- SRH 0-1km AGL: 22 m2/s2",
                    "LINE07": "- EBShear: 0.0 kts",
                    "LINE08": "- MeanWind 1-3kmAGL: 13.7 kts",
                    "LINE09": "- MLCAPE/MLCIN: 0/-999 J/kg",
                    "LINE10": "Avg. beam height (ARL): 6.77 kft / 2.06 km"
                },
                "probhail": {
                    "PROB": "0",
                    "LINE01": "ProbHail: 0%",
                    "LINE02": "- MESH: 1.03 in. (flagged)",
                    "LINE03": "- Flash Rate: 0 fl/min",
                    "LINE04": "- Norm. vert. growth rate: N/A",
                    "LINE05": "- EBShear: 0.0 kts",
                    "LINE06": "- CAPE -10C to -30C: 0 J/kg",
                    "LINE07": "- PWAT: 0.3 in.",
                    "LINE08": "- Wetbulb 0C hgt: 6.4 kft AGL"
                },
                "probwind": {
                    "PROB": "1",
                    "LINE01": "ProbWind: 1%",
                    "LINE02": "- MESH: 1.03 in. (flagged)",
                    "LINE03": "- VIL Density: 2.54 g/m^3",
                    "LINE04": "- Flash Rate: 0 fl/min",
                    "LINE05": "- 98% LLAzShear: 0.001 /s (weak)",
                    "LINE06": "- 98% MLAzShear: 0.001 /s (weak)",
                    "LINE07": "- Norm. vert. growth rate: N/A",
                    "LINE08": "- EBShear: 0.0 kts",
                    "LINE09": "- MeanWind 1-3kmAGL: 13.7 kts",
                    "LINE10": "- MUCAPE: 0 J/kg; MLCAPE: 0 J/kg"
                }
            },
            "properties": {
                "MUCAPE": "0",
                "MLCAPE": "0",
                "MLCIN": "-999",
                "EBSHEAR": "0.0",
                "SRH01KM": "22",
                "MEANWIND_1-3kmAGL": "13.7",
                "MESH": "1.03",
                "VIL_DENSITY": "2.54",
                "FLASH_RATE": "0",
                "FLASH_DENSITY": "0.00",
                "MAXLLAZ": "0.001",
                "P98LLAZ": "0.001",
                "P98MLAZ": "0.001",
                "MAXRC_EMISS": "N/A",
                "MAXRC_ICECF": "N/A",
                "WETBULB_0C_HGT": "6.4",
                "PWAT": "0.3",
                "CAPE_M10M30": "0",
                "LJA": "0.0",
                "SIZE": "107",
                "AVG_BEAM_HGT": "6.77 kft / 2.06 km",
                "MOTION_EAST": "0.895",
                "MOTION_SOUTH": "-9.521",
                "PS": "0",
                "ID": "128715"
            }
        },
        {
            "type": "Feature",
            "geometry": {
                "type": "Polygon",
                "coordinates": [
                    [
                        [
                            -82.73,
                            26.37
                        ],
                        [
                            -82.67,
                            26.37
                        ],
                        [
                            -82.68,
                            26.35
                        ],
                        [
                            -82.66,
                            26.33
                        ],
                        [
                            -82.67,
                            26.32
                        ],
                        [
                            -82.67,
                            26.3
                        ],
                        [
                            -82.66,
                            26.29
                        ],
                        [
                            -82.66,
                            26.24
                        ],
                        [
                            -82.63,
                            26.21
                        ],
                        [
                            -82.62,
                            26.21
                        ],
                        [
                            -82.63,
                            26.19
                        ],
                        [
                            -82.67,
                            26.2
                        ],
                        [
                            -82.68,
                            26.22
                        ],
                        [
                            -82.67,
                            26.24
                        ],
                        [
                            -82.71,
                            26.26
                        ],
                        [
                            -82.71,
                            26.27
                        ],
                        [
                            -82.73,
                            26.28
                        ],
                        [
                            -82.73,
                            26.31
                        ],
                        [
                            -82.74,
                            26.32
                        ],
                        [
                            -82.72,
                            26.34
                        ],
                        [
                            -82.72,
                            26.35
                        ],
                        [
                            -82.74,
                            26.36
                        ],
                        [
                            -82.73,
                            26.37
                        ]
                    ]
                ]
            },
            "models": {
                "probsevere": {
                    "PROB": "1",
                    "LINE01": "ProbHail: 0%; ProbWind: 1%; ProbTor: 0%",
                    "LINE02": "- MESH: 0.00 in.",
                    "LINE03": "- VIL Density: 1.42 g/m^3",
                    "LINE04": "- Flash Rate: 0 fl/min",
                    "LINE05": "- Flash Density (max in last 30 min): 0.00 fl/min/km^2",
                    "LINE06": "- Max LLAzShear: 0.004 /s",
                    "LINE07": "- 98% LLAzShear: 0.004 /s",
                    "LINE08": "- 98% MLAzShear: 0.003 /s",
                    "LINE09": "- Norm. vert. growth rate: N/A",
                    "LINE10": "- EBShear: 21.5 kts; SRH 0-1km AGL: 18 m^2/s^2",
                    "LINE11": "- MUCAPE: 2671 J/kg; MLCAPE: 2117 J/kg; MLCIN: -1 J/kg",
                    "LINE12": "- MeanWind 1-3kmAGL: 6.6 kts",
                    "LINE13": "- Wetbulb 0C hgt: 13.4 kft AGL",
                    "LINE14": "- CAPE -10C to -30C: 610 J/kg; PWAT: 1.8 in.",
                    "LINE15": "Avg. beam height (ARL): 8.04 kft / 2.45 km"
                },
                "probtor": {
                    "PROB": "0",
                    "LINE01": "ProbTor: 0%",
                    "LINE02": "- Max LLAzShear: 0.004 /s (weak)",
                    "LINE03": "- 98% LLAzShear: 0.004 /s (weak)",
                    "LINE04": "- 98% MLAzShear: 0.003 /s (weak)",
                    "LINE05": "- Flash Density: 0.00 fl/min/km^2",
                    "LINE06": "- SRH 0-1km AGL: 18 m2/s2",
                    "LINE07": "- EBShear: 21.5 kts",
                    "LINE08": "- MeanWind 1-3kmAGL: 6.6 kts",
                    "LINE09": "- MLCAPE/MLCIN: 2117/-1 J/kg",
                    "LINE10": "Avg. beam height (ARL): 8.04 kft / 2.45 km"
                },
                "probhail": {
                    "PROB": "0",
                    "LINE01": "ProbHail: 0%",
                    "LINE02": "- MESH: 0.00 in.",
                    "LINE03": "- Flash Rate: 0 fl/min",
                    "LINE04": "- Norm. vert. growth rate: N/A",
                    "LINE05": "- EBShear: 21.5 kts",
                    "LINE06": "- CAPE -10C to -30C: 610 J/kg",
                    "LINE07": "- PWAT: 1.8 in.",
                    "LINE08": "- Wetbulb 0C hgt: 13.4 kft AGL"
                },
                "probwind": {
                    "PROB": "1",
                    "LINE01": "ProbWind: 1%",
                    "LINE02": "- MESH: 0.00 in.",
                    "LINE03": "- VIL Density: 1.42 g/m^3",
                    "LINE04": "- Flash Rate: 0 fl/min",
                    "LINE05": "- 98% LLAzShear: 0.004 /s (weak)",
                    "LINE06": "- 98% MLAzShear: 0.003 /s (weak)",
                    "LINE07": "- Norm. vert. growth rate: N/A",
                    "LINE08": "- EBShear: 21.5 kts",
                    "LINE09": "- MeanWind 1-3kmAGL: 6.6 kts",
                    "LINE10": "- MUCAPE: 2671 J/kg; MLCAPE: 2117 J/kg"
                }
            },
            "properties": {
                "MUCAPE": "2671",
                "MLCAPE": "2117",
                "MLCIN": "-1",
                "EBSHEAR": "21.5",
                "SRH01KM": "18",
                "MEANWIND_1-3kmAGL": "6.6",
                "MESH": "0.00",
                "VIL_DENSITY": "1.42",
                "FLASH_RATE": "0",
                "FLASH_DENSITY": "0.00",
                "MAXLLAZ": "0.004",
                "P98LLAZ": "0.004",
                "P98MLAZ": "0.003",
                "MAXRC_EMISS": "N/A",
                "MAXRC_ICECF": "N/A",
                "WETBULB_0C_HGT": "13.4",
                "PWAT": "1.8",
                "CAPE_M10M30": "610",
                "LJA": "0.0",
                "SIZE": "112",
                "AVG_BEAM_HGT": "8.04 kft / 2.45 km",
                "MOTION_EAST": "0.895",
                "MOTION_SOUTH": "-9.521",
                "PS": "1",
                "ID": "128739"
            }
        },
        {
            "type": "Feature",
            "geometry": {
                "type": "Polygon",
                "coordinates": [
                    [
                        [
                            -76.0,
                            43.35
                        ],
                        [
                            -75.96,
                            43.35
                        ],
                        [
                            -75.95,
                            43.34
                        ],
                        [
                            -75.95,
                            43.3
                        ],
                        [
                            -75.96,
                            43.29
                        ],
                        [
                            -76.0,
                            43.29
                        ],
                        [
                            -76.01,
                            43.3
                        ],
                        [
                            -76.01,
                            43.34
                        ],
                        [
                            -76.0,
                            43.35
                        ]
                    ]
                ]
            },
            "models": {
                "probsevere": {
                    "PROB": "1",
                    "LINE01": "ProbHail: 0%; ProbWind: 1%; ProbTor: 0%",
                    "LINE02": "- MESH: 0.00 in.",
                    "LINE03": "- VIL Density: 0.35 g/m^3",
                    "LINE04": "- Flash Rate: 0 fl/min",
                    "LINE05": "- Flash Density (max in last 30 min): 0.00 fl/min/km^2",
                    "LINE06": "- Max LLAzShear: 0.001 /s",
                    "LINE07": "- 98% LLAzShear: 0.001 /s",
                    "LINE08": "- 98% MLAzShear: 0.001 /s",
                    "LINE09": "- Norm. vert. growth rate: 1456Z 0.4%/min (weak)",
                    "LINE10": "- EBShear: 13.0 kts; SRH 0-1km AGL: 68 m^2/s^2",
                    "LINE11": "- MUCAPE: 381 J/kg; MLCAPE: 271 J/kg; MLCIN: -999 J/kg",
                    "LINE12": "- MeanWind 1-3kmAGL: 22.1 kts",
                    "LINE13": "- Wetbulb 0C hgt: 4.9 kft AGL",
                    "LINE14": "- CAPE -10C to -30C: 87 J/kg; PWAT: 0.8 in.",
                    "LINE15": "Avg. beam height (ARL): 1.90 kft / 0.58 km"
                },
                "probtor": {
                    "PROB": "0",
                    "LINE01": "ProbTor: 0%",
                    "LINE02": "- Max LLAzShear: 0.001 /s (weak)",
                    "LINE03": "- 98% LLAzShear: 0.001 /s (weak)",
                    "LINE04": "- 98% MLAzShear: 0.001 /s (weak)",
                    "LINE05": "- Flash Density: 0.00 fl/min/km^2",
                    "LINE06": "- SRH 0-1km AGL: 68 m2/s2",
                    "LINE07": "- EBShear: 13.0 kts",
                    "LINE08": "- MeanWind 1-3kmAGL: 22.1 kts",
                    "LINE09": "- MLCAPE/MLCIN: 271/-999 J/kg",
                    "LINE10": "Avg. beam height (ARL): 1.90 kft / 0.58 km"
                },
                "probhail": {
                    "PROB": "0",
                    "LINE01": "ProbHail: 0%",
                    "LINE02": "- MESH: 0.00 in.",
                    "LINE03": "- Flash Rate: 0 fl/min",
                    "LINE04": "- Norm. vert. growth rate: 1456Z 0.4%/min (weak)",
                    "LINE05": "- EBShear: 13.0 kts",
                    "LINE06": "- CAPE -10C to -30C: 87 J/kg",
                    "LINE07": "- PWAT: 0.8 in.",
                    "LINE08": "- Wetbulb 0C hgt: 4.9 kft AGL"
                },
                "probwind": {
                    "PROB": "1",
                    "LINE01": "ProbWind: 1%",
                    "LINE02": "- MESH: 0.00 in.",
                    "LINE03": "- VIL Density: 0.35 g/m^3",
                    "LINE04": "- Flash Rate: 0 fl/min",
                    "LINE05": "- 98% LLAzShear: 0.001 /s (weak)",
                    "LINE06": "- 98% MLAzShear: 0.001 /s (weak)",
                    "LINE07": "- Norm. vert. growth rate: 1456Z 0.4%/min (weak)",
                    "LINE08": "- EBShear: 13.0 kts",
                    "LINE09": "- MeanWind 1-3kmAGL: 22.1 kts",
                    "LINE10": "- MUCAPE: 381 J/kg; MLCAPE: 271 J/kg"
                }
            },
            "properties": {
                "MUCAPE": "381",
                "MLCAPE": "271",
                "MLCIN": "-999",
                "EBSHEAR": "13.0",
                "SRH01KM": "68",
                "MEANWIND_1-3kmAGL": "22.1",
                "MESH": "0.00",
                "VIL_DENSITY": "0.35",
                "FLASH_RATE": "0",
                "FLASH_DENSITY": "0.00",
                "MAXLLAZ": "0.001",
                "P98LLAZ": "0.001",
                "P98MLAZ": "0.001",
                "MAXRC_EMISS": "1456Z 0.4%/min (weak)",
                "MAXRC_ICECF": "1456Z 0.0/min (weak)",
                "WETBULB_0C_HGT": "4.9",
                "PWAT": "0.8",
                "CAPE_M10M30": "87",
                "LJA": "0.0",
                "SIZE": "45",
                "AVG_BEAM_HGT": "1.90 kft / 0.58 km",
                "MOTION_EAST": "0.895",
                "MOTION_SOUTH": "-9.521",
                "PS": "0",
                "ID": "128741"
            }
        },
        {
            "type": "Feature",
            "geometry": {
                "type": "Polygon",
                "coordinates": [
                    [
                        [
                            -76.21,
                            43.47
                        ],
                        [
                            -76.14,
                            43.47
                        ],
                        [
                            -76.12,
                            43.46
                        ],
                        [
                            -76.12,
                            43.41
                        ],
                        [
                            -76.11,
                            43.4
                        ],
                        [
                            -76.14,
                            43.37
                        ],
                        [
                            -76.19,
                            43.38
                        ],
                        [
                            -76.22,
                            43.41
                        ],
                        [
                            -76.22,
                            43.46
                        ],
                        [
                            -76.21,
                            43.47
                        ]
                    ]
                ]
            },
            "models": {
                "probsevere": {
                    "PROB": "1",
                    "LINE01": "ProbHail: 0%; ProbWind: 1%; ProbTor: 0%",
                    "LINE02": "- MESH: 0.00 in.",
                    "LINE03": "- VIL Density: 0.54 g/m^3",
                    "LINE04": "- Flash Rate: 0 fl/min",
                    "LINE05": "- Flash Density (max in last 30 min): 0.00 fl/min/km^2",
                    "LINE06": "- Max LLAzShear: 0.003 /s",
                    "LINE07": "- 98% LLAzShear: 0.002 /s",
                    "LINE08": "- 98% MLAzShear: 0.001 /s",
                    "LINE09": "- Norm. vert. growth rate: N/A",
                    "LINE10": "- EBShear: 10.9 kts; SRH 0-1km AGL: 47 m^2/s^2",
                    "LINE11": "- MUCAPE: 393 J/kg; MLCAPE: 277 J/kg; MLCIN: -1 J/kg",
                    "LINE12": "- MeanWind 1-3kmAGL: 21.7 kts",
                    "LINE13": "- Wetbulb 0C hgt: 4.9 kft AGL",
                    "LINE14": "- CAPE -10C to -30C: 75 J/kg; PWAT: 0.8 in.",
                    "LINE15": "Avg. beam height (ARL): 2.20 kft / 0.67 km"
                },
                "probtor": {
                    "PROB": "0",
                    "LINE01": "ProbTor: 0%",
                    "LINE02": "- Max LLAzShear: 0.003 /s (weak)",
                    "LINE03": "- 98% LLAzShear: 0.002 /s (weak)",
                    "LINE04": "- 98% MLAzShear: 0.001 /s (weak)",
                    "LINE05": "- Flash Density: 0.00 fl/min/km^2",
                    "LINE06": "- SRH 0-1km AGL: 47 m2/s2",
                    "LINE07": "- EBShear: 10.9 kts",
                    "LINE08": "- MeanWind 1-3kmAGL: 21.7 kts",
                    "LINE09": "- MLCAPE/MLCIN: 277/-1 J/kg",
                    "LINE10": "Avg. beam height (ARL): 2.20 kft / 0.67 km"
                },
                "probhail": {
                    "PROB": "0",
                    "LINE01": "ProbHail: 0%",
                    "LINE02": "- MESH: 0.00 in.",
                    "LINE03": "- Flash Rate: 0 fl/min",
                    "LINE04": "- Norm. vert. growth rate: N/A",
                    "LINE05": "- EBShear: 10.9 kts",
                    "LINE06": "- CAPE -10C to -30C: 75 J/kg",
                    "LINE07": "- PWAT: 0.8 in.",
                    "LINE08": "- Wetbulb 0C hgt: 4.9 kft AGL"
                },
                "probwind": {
                    "PROB": "1",
                    "LINE01": "ProbWind: 1%",
                    "LINE02": "- MESH: 0.00 in.",
                    "LINE03": "- VIL Density: 0.54 g/m^3",
                    "LINE04": "- Flash Rate: 0 fl/min",
                    "LINE05": "- 98% LLAzShear: 0.002 /s (weak)",
                    "LINE06": "- 98% MLAzShear: 0.001 /s (weak)",
                    "LINE07": "- Norm. vert. growth rate: N/A",
                    "LINE08": "- EBShear: 10.9 kts",
                    "LINE09": "- MeanWind 1-3kmAGL: 21.7 kts",
                    "LINE10": "- MUCAPE: 393 J/kg; MLCAPE: 277 J/kg"
                }
            },
            "properties": {
                "MUCAPE": "393",
                "MLCAPE": "277",
                "MLCIN": "-1",
                "EBSHEAR": "10.9",
                "SRH01KM": "47",
                "MEANWIND_1-3kmAGL": "21.7",
                "MESH": "0.00",
                "VIL_DENSITY": "0.54",
                "FLASH_RATE": "0",
                "FLASH_DENSITY": "0.00",
                "MAXLLAZ": "0.003",
                "P98LLAZ": "0.002",
                "P98MLAZ": "0.001",
                "MAXRC_EMISS": "N/A",
                "MAXRC_ICECF": "N/A",
                "WETBULB_0C_HGT": "4.9",
                "PWAT": "0.8",
                "CAPE_M10M30": "75",
                "LJA": "0.0",
                "SIZE": "104",
                "AVG_BEAM_HGT": "2.20 kft / 0.67 km",
                "MOTION_EAST": "0.895",
                "MOTION_SOUTH": "-9.521",
                "PS": "0",
                "ID": "128742"
            }
        },
        {
            "type": "Feature",
            "geometry": {
                "type": "Polygon",
                "coordinates": [
                    [
                        [
                            -66.65,
                            46.77
                        ],
                        [
                            -66.6,
                            46.77
                        ],
                        [
                            -66.53,
                            46.73
                        ],
                        [
                            -66.53,
                            46.67
                        ],
                        [
                            -66.61,
                            46.67
                        ],
                        [
                            -66.65,
                            46.69
                        ],
                        [
                            -66.66,
                            46.7
                        ],
                        [
                            -66.66,
                            46.74
                        ],
                        [
                            -66.65,
                            46.75
                        ],
                        [
                            -66.65,
                            46.77
                        ]
                    ]
                ]
            },
            "models": {
                "probsevere": {
                    "PROB": "1",
                    "LINE01": "ProbHail: 0%; ProbWind: 1%; ProbTor: 0%",
                    "LINE02": "- MESH: 0.00 in.",
                    "LINE03": "- VIL Density: 0.67 g/m^3",
                    "LINE04": "- Flash Rate: 0 fl/min",
                    "LINE05": "- Flash Density (max in last 30 min): 0.00 fl/min/km^2",
                    "LINE06": "- Max LLAzShear: 0.002 /s",
                    "LINE07": "- 98% LLAzShear: 0.002 /s",
                    "LINE08": "- 98% MLAzShear: 0.001 /s",
                    "LINE09": "- Norm. vert. growth rate: 1441Z 0.7%/min (weak)",
                    "LINE10": "- EBShear: 14.8 kts; SRH 0-1km AGL: 83 m^2/s^2",
                    "LINE11": "- MUCAPE: 59 J/kg; MLCAPE: 10 J/kg; MLCIN: -6 J/kg",
                    "LINE12": "- MeanWind 1-3kmAGL: 38.5 kts",
                    "LINE13": "- Wetbulb 0C hgt: 9.5 kft AGL",
                    "LINE14": "- CAPE -10C to -30C: 0 J/kg; PWAT: 1.3 in.",
                    "LINE15": "Avg. beam height (ARL): 7.58 kft / 2.31 km"
                },
                "probtor": {
                    "PROB": "0",
                    "LINE01": "ProbTor: 0%",
                    "LINE02": "- Max LLAzShear: 0.002 /s (weak)",
                    "LINE03": "- 98% LLAzShear: 0.002 /s (weak)",
                    "LINE04": "- 98% MLAzShear: 0.001 /s (weak)",
                    "LINE05": "- Flash Density: 0.00 fl/min/km^2",
                    "LINE06": "- SRH 0-1km AGL: 83 m2/s2",
                    "LINE07": "- EBShear: 14.8 kts",
                    "LINE08": "- MeanWind 1-3kmAGL: 38.5 kts",
                    "LINE09": "- MLCAPE/MLCIN: 10/-6 J/kg",
                    "LINE10": "Avg. beam height (ARL): 7.58 kft / 2.31 km"
                },
                "probhail": {
                    "PROB": "0",
                    "LINE01": "ProbHail: 0%",
                    "LINE02": "- MESH: 0.00 in.",
                    "LINE03": "- Flash Rate: 0 fl/min",
                    "LINE04": "- Norm. vert. growth rate: 1441Z 0.7%/min (weak)",
                    "LINE05": "- EBShear: 14.8 kts",
                    "LINE06": "- CAPE -10C to -30C: 0 J/kg",
                    "LINE07": "- PWAT: 1.3 in.",
                    "LINE08": "- Wetbulb 0C hgt: 9.5 kft AGL"
                },
                "probwind": {
                    "PROB": "1",
                    "LINE01": "ProbWind: 1%",
                    "LINE02": "- MESH: 0.00 in.",
                    "LINE03": "- VIL Density: 0.67 g/m^3",
                    "LINE04": "- Flash Rate: 0 fl/min",
                    "LINE05": "- 98% LLAzShear: 0.002 /s (weak)",
                    "LINE06": "- 98% MLAzShear: 0.001 /s (weak)",
                    "LINE07": "- Norm. vert. growth rate: 1441Z 0.7%/min (weak)",
                    "LINE08": "- EBShear: 14.8 kts",
                    "LINE09": "- MeanWind 1-3kmAGL: 38.5 kts",
                    "LINE10": "- MUCAPE: 59 J/kg; MLCAPE: 10 J/kg"
                }
            },
            "properties": {
                "MUCAPE": "59",
                "MLCAPE": "10",
                "MLCIN": "-6",
                "EBSHEAR": "14.8",
                "SRH01KM": "83",
                "MEANWIND_1-3kmAGL": "38.5",
                "MESH": "0.00",
                "VIL_DENSITY": "0.67",
                "FLASH_RATE": "0",
                "FLASH_DENSITY": "0.00",
                "MAXLLAZ": "0.002",
                "P98LLAZ": "0.002",
                "P98MLAZ": "0.001",
                "MAXRC_EMISS": "1441Z 0.7%/min (weak)",
                "MAXRC_ICECF": "1441Z 0.0/min (weak)",
                "WETBULB_0C_HGT": "9.5",
                "PWAT": "1.3",
                "CAPE_M10M30": "0",
                "LJA": "0.0",
                "SIZE": "125",
                "AVG_BEAM_HGT": "7.58 kft / 2.31 km",
                "MOTION_EAST": "0.895",
                "MOTION_SOUTH": "-9.521",
                "PS": "0",
                "ID": "128744"
            }
        },
        {
            "type": "Feature",
            "geometry": {
                "type": "Polygon",
                "coordinates": [
                    [
                        [
                            -98.54,
                            42.67
                        ],
                        [
                            -98.53,
                            42.67
                        ],
                        [
                            -98.52,
                            42.67
                        ],
                        [
                            -98.51,
                            42.66
                        ],
                        [
                            -98.5,
                            42.66
                        ],
                        [
                            -98.49,
                            42.66
                        ],
                        [
                            -98.48,
                            42.66
                        ],
                        [
                            -98.47,
                            42.66
                        ],
                        [
                            -98.46,
                            42.66
                        ],
                        [
                            -98.45,
                            42.66
                        ],
                        [
                            -98.46,
                            42.66
                        ],
                        [
                            -98.47,
                            42.66
                        ],
                        [
                            -98.48,
                            42.66
                        ],
                        [
                            -98.49,
                            42.66
                        ],
                        [
                            -98.5,
                            42.66
                        ],
                        [
                            -98.51,
                            42.65
                        ],
                        [
                            -98.52,
                            42.65
                        ],
                        [
                            -98.53,
                            42.64
                        ],
                        [
                            -98.53,
                            42.63
                        ],
                        [
                            -98.53,
                            42.62
                        ],
                        [
                            -98.53,
                            42.61
                        ],
                        [
                            -98.53,
                            42.6
                        ],
                        [
                            -98.52,
                            42.59
                        ],
                        [
                            -98.51,
                            42.6
                        ],
                        [
                            -98.5,
                            42.61
                        ],
                        [
                            -98.5,
                            42.62
                        ],
                        [
                            -98.49,
                            42.62
                        ],
                        [
                            -98.48,
                            42.62
                        ],
                        [
                            -98.47,
                            42.62
                        ],
                        [
                            -98.46,
                            42.62
                        ],
                        [
                            -98.45,
                            42.62
                        ],
                        [
                            -98.44,
                            42.62
                        ],
                        [
                            -98.43,
                            42.63
                        ],
                        [
                            -98.42,
                            42.63
                        ],
                        [
                            -98.41,
                            42.63
                        ],
                        [
                            -98.41,
                            42.62
                        ],
                        [
                            -98.41,
                            42.61
                        ],
                        [
                            -98.41,
                            42.6
                        ],
                        [
                            -98.41,
                            42.59
                        ],
                        [
                            -98.41,
                            42.58
                        ],
                        [
                            -98.41,
                            42.57
                        ],
                        [
                            -98.41,
                            42.56
                        ],
                        [
                            -98.41,
                            42.55
                        ],
                        [
                            -98.41,
                            42.54
                        ],
                        [
                            -98.41,
                            42.53
                        ],
                        [
                            -98.42,
                            42.53
                        ],
                        [
                            -98.43,
                            42.52
                        ],
                        [
                            -98.44,
                            42.52
                        ],
                        [
                            -98.45,
                            42.52
                        ],
                        [
                            -98.46,
                            42.52
                        ],
                        [
                            -98.47,
                            42.52
                        ],
                        [
                            -98.48,
                            42.52
                        ],
                        [
                            -98.49,
                            42.52
                        ],
                        [
                            -98.5,
                            42.52
                        ],
                        [
                            -98.51,
                            42.52
                        ],
                        [
                            -98.52,
                            42.53
                        ],
                        [
                            -98.53,
                            42.53
                        ],
                        [
                            -98.53,
                            42.54
                        ],
                        [
                            -98.53,
                            42.55
                        ],
                        [
                            -98.53,
                            42.56
                        ],
                        [
                            -98.53,
                            42.55
                        ],
                        [
                            -98.52,
                            42.54
                        ],
                        [
                            -98.51,
                            42.55
                        ],
                        [
                            -98.51,
                            42.56
                        ],
                        [
                            -98.51,
                            42.57
                        ],
                        [
                            -98.51,
                            42.58
                        ],
                        [
                            -98.52,
                            42.59
                        ],
                        [
                            -98.53,
                            42.58
                        ],
                        [
                            -98.54,
                            42.58
                        ],
                        [
                            -98.55,
                            42.58
                        ],
                        [
                            -98.55,
                            42.59
                        ],
                        [
                            -98.55,
                            42.6
                        ],
                        [
                            -98.55,
                            42.61
                        ],
                        [
                            -98.55,
                            42.62
                        ],
                        [
                            -98.55,
                            42.63
                        ],
                        [
                            -98.55,
                            42.64
                        ],
                        [
                            -98.55,
                            42.65
                        ],
                        [
                            -98.55,
                            42.66
                        ],
                        [
                            -98.54,
                            42.67
                        ]
                    ]
                ]
            },
            "models": {
                "probsevere": {
                    "PROB": "1",
                    "LINE01": "ProbHail: 0%; ProbWind: 1%; ProbTor: 0%",
                    "LINE02": "- MESH: 0.38 in.",
                    "LINE03": "- VIL Density: 1.74 g/m^3",
                    "LINE04": "- Flash Rate: 0 fl/min",
                    "LINE05": "- Flash Density (max in last 30 min): 0.00 fl/min/km^2",
                    "LINE06": "- Max LLAzShear: 0.003 /s",
                    "LINE07": "- 98% LLAzShear: 0.002 /s",
                    "LINE08": "- 98% MLAzShear: 0.002 /s",
                    "LINE09": "- Norm. vert. growth rate: N/A",
                    "LINE10": "- EBShear: 0.0 kts; SRH 0-1km AGL: 13 m^2/s^2",
                    "LINE11": "- MUCAPE: 0 J/kg; MLCAPE: 0 J/kg; MLCIN: -999 J/kg",
                    "LINE12": "- MeanWind 1-3kmAGL: 11.3 kts",
                    "LINE13": "- Wetbulb 0C hgt: 7.5 kft AGL",
                    "LINE14": "- CAPE -10C to -30C: 0 J/kg; PWAT: 0.5 in.",
                    "LINE15": "Avg. beam height (ARL): 13.60 kft / 4.15 km"
                },
                "probtor": {
                    "PROB": "0",
                    "LINE01": "ProbTor: 0%",
                    "LINE02": "- Max LLAzShear: 0.003 /s (weak)",
                    "LINE03": "- 98% LLAzShear: 0.002 /s (weak)",
                    "LINE04": "- 98% MLAzShear: 0.002 /s (weak)",
                    "LINE05": "- Flash Density: 0.00 fl/min/km^2",
                    "LINE06": "- SRH 0-1km AGL: 13 m2/s2",
                    "LINE07": "- EBShear: 0.0 kts",
                    "LINE08": "- MeanWind 1-3kmAGL: 11.3 kts",
                    "LINE09": "- MLCAPE/MLCIN: 0/-999 J/kg",
                    "LINE10": "Avg. beam height (ARL): 13.60 kft / 4.15 km"
                },
                "probhail": {
                    "PROB": "0",
                    "LINE01": "ProbHail: 0%",
                    "LINE02": "- MESH: 0.38 in.",
                    "LINE03": "- Flash Rate: 0 fl/min",
                    "LINE04": "- Norm. vert. growth rate: N/A",
                    "LINE05": "- EBShear: 0.0 kts",
                    "LINE06": "- CAPE -10C to -30C: 0 J/kg",
                    "LINE07": "- PWAT: 0.5 in.",
                    "LINE08": "- Wetbulb 0C hgt: 7.5 kft AGL"
                },
                "probwind": {
                    "PROB": "1",
                    "LINE01": "ProbWind: 1%",
                    "LINE02": "- MESH: 0.38 in.",
                    "LINE03": "- VIL Density: 1.74 g/m^3",
                    "LINE04": "- Flash Rate: 0 fl/min",
                    "LINE05": "- 98% LLAzShear: 0.002 /s (weak)",
                    "LINE06": "- 98% MLAzShear: 0.002 /s (weak)",
                    "LINE07": "- Norm. vert. growth rate: N/A",
                    "LINE08": "- EBShear: 0.0 kts",
                    "LINE09": "- MeanWind 1-3kmAGL: 11.3 kts",
                    "LINE10": "- MUCAPE: 0 J/kg; MLCAPE: 0 J/kg"
                }
            },
            "properties": {
                "MUCAPE": "0",
                "MLCAPE": "0",
                "MLCIN": "-999",
                "EBSHEAR": "0.0",
                "SRH01KM": "13",
                "MEANWIND_1-3kmAGL": "11.3",
                "MESH": "0.38",
                "VIL_DENSITY": "1.74",
                "FLASH_RATE": "0",
                "FLASH_DENSITY": "0.00",
                "MAXLLAZ": "0.003",
                "P98LLAZ": "0.002",
                "P98MLAZ": "0.002",
                "MAXRC_EMISS": "N/A",
                "MAXRC_ICECF": "N/A",
                "WETBULB_0C_HGT": "7.5",
                "PWAT": "0.5",
                "CAPE_M10M30": "0",
                "LJA": "0.0",
                "SIZE": "167",
                "AVG_BEAM_HGT": "13.60 kft / 4.15 km",
                "MOTION_EAST": "0.895",
                "MOTION_SOUTH": "-9.521",
                "PS": "0",
                "ID": "128745"
            }
        },
        {
            "type": "Feature",
            "geometry": {
                "type": "Polygon",
                "coordinates": [
                    [
                        [
                            -98.56,
                            37.43
                        ],
                        [
                            -98.54,
                            37.42
                        ],
                        [
                            -98.55,
                            37.37
                        ],
                        [
                            -98.53,
                            37.36
                        ],
                        [
                            -98.53,
                            37.34
                        ],
                        [
                            -98.57,
                            37.33
                        ],
                        [
                            -98.57,
                            37.42
                        ],
                        [
                            -98.56,
                            37.43
                        ]
                    ]
                ]
            },
            "models": {
                "probsevere": {
                    "PROB": "1",
                    "LINE01": "ProbHail: 0%; ProbWind: 1%; ProbTor: 0%",
                    "LINE02": "- MESH: 0.00 in.",
                    "LINE03": "- VIL Density: 0.00 g/m^3",
                    "LINE04": "- Flash Rate: 0 fl/min",
                    "LINE05": "- Flash Density (max in last 30 min): 0.00 fl/min/km^2",
                    "LINE06": "- Max LLAzShear: 0.000 /s",
                    "LINE07": "- 98% LLAzShear: 0.000 /s",
                    "LINE08": "- 98% MLAzShear: 0.000 /s",
                    "LINE09": "- Norm. vert. growth rate: N/A",
                    "LINE10": "- EBShear: 0.0 kts; SRH 0-1km AGL: 13 m^2/s^2",
                    "LINE11": "- MUCAPE: 0 J/kg; MLCAPE: 0 J/kg; MLCIN: -999 J/kg",
                    "LINE12": "- MeanWind 1-3kmAGL: 11.0 kts",
                    "LINE13": "- Wetbulb 0C hgt: 7.8 kft AGL",
                    "LINE14": "- CAPE -10C to -30C: 0 J/kg; PWAT: 0.4 in.",
                    "LINE15": "Avg. beam height (ARL): 3.15 kft / 0.96 km"
                },
                "probtor": {
                    "PROB": "0",
                    "LINE01": "ProbTor: 0%",
                    "LINE02": "- Max LLAzShear: 0.000 /s (weak)",
                    "LINE03": "- 98% LLAzShear: 0.000 /s (weak)",
                    "LINE04": "- 98% MLAzShear: 0.000 /s (weak)",
                    "LINE05": "- Flash Density: 0.00 fl/min/km^2",
                    "LINE06": "- SRH 0-1km AGL: 13 m2/s2",
                    "LINE07": "- EBShear: 0.0 kts",
                    "LINE08": "- MeanWind 1-3kmAGL: 11.0 kts",
                    "LINE09": "- MLCAPE/MLCIN: 0/-999 J/kg",
                    "LINE10": "Avg. beam height (ARL): 3.15 kft / 0.96 km"
                },
                "probhail": {
                    "PROB": "0",
                    "LINE01": "ProbHail: 0%",
                    "LINE02": "- MESH: 0.00 in.",
                    "LINE03": "- Flash Rate: 0 fl/min",
                    "LINE04": "- Norm. vert. growth rate: N/A",
                    "LINE05": "- EBShear: 0.0 kts",
                    "LINE06": "- CAPE -10C to -30C: 0 J/kg",
                    "LINE07": "- PWAT: 0.4 in.",
                    "LINE08": "- Wetbulb 0C hgt: 7.8 kft AGL"
                },
                "probwind": {
                    "PROB": "1",
                    "LINE01": "ProbWind: 1%",
                    "LINE02": "- MESH: 0.00 in.",
                    "LINE03": "- VIL Density: 0.00 g/m^3",
                    "LINE04": "- Flash Rate: 0 fl/min",
                    "LINE05": "- 98% LLAzShear: 0.000 /s (weak)",
                    "LINE06": "- 98% MLAzShear: 0.000 /s (weak)",
                    "LINE07": "- Norm. vert. growth rate: N/A",
                    "LINE08": "- EBShear: 0.0 kts",
                    "LINE09": "- MeanWind 1-3kmAGL: 11.0 kts",
                    "LINE10": "- MUCAPE: 0 J/kg; MLCAPE: 0 J/kg"
                }
            },
            "properties": {
                "MUCAPE": "0",
                "MLCAPE": "0",
                "MLCIN": "-999",
                "EBSHEAR": "0.0",
                "SRH01KM": "13",
                "MEANWIND_1-3kmAGL": "11.0",
                "MESH": "0.00",
                "VIL_DENSITY": "0.00",
                "FLASH_RATE": "0",
                "FLASH_DENSITY": "0.00",
                "MAXLLAZ": "0.000",
                "P98LLAZ": "0.000",
                "P98MLAZ": "0.000",
                "MAXRC_EMISS": "N/A",
                "MAXRC_ICECF": "N/A",
                "WETBULB_0C_HGT": "7.8",
                "PWAT": "0.4",
                "CAPE_M10M30": "0",
                "LJA": "0.0",
                "SIZE": "40",
                "AVG_BEAM_HGT": "3.15 kft / 0.96 km",
                "MOTION_EAST": "0.895",
                "MOTION_SOUTH": "-9.521",
                "PS": "0",
                "ID": "128747"
            }
        },
        {
            "type": "Feature",
            "geometry": {
                "type": "Polygon",
                "coordinates": [
                    [
                        [
                            -76.4,
                            43.37
                        ],
                        [
                            -76.34,
                            43.37
                        ],
                        [
                            -76.32,
                            43.34
                        ],
                        [
                            -76.32,
                            43.29
                        ],
                        [
                            -76.33,
                            43.27
                        ],
                        [
                            -76.39,
                            43.24
                        ],
                        [
                            -76.4,
                            43.24
                        ],
                        [
                            -76.4,
                            43.26
                        ],
                        [
                            -76.42,
                            43.3
                        ],
                        [
                            -76.4,
                            43.32
                        ],
                        [
                            -76.42,
                            43.36
                        ],
                        [
                            -76.4,
                            43.37
                        ]
                    ]
                ]
            },
            "models": {
                "probsevere": {
                    "PROB": "1",
                    "LINE01": "ProbHail: 0%; ProbWind: 1%; ProbTor: 0%",
                    "LINE02": "- MESH: 0.00 in.",
                    "LINE03": "- VIL Density: 0.31 g/m^3",
                    "LINE04": "- Flash Rate: 0 fl/min",
                    "LINE05": "- Flash Density (max in last 30 min): 0.00 fl/min/km^2",
                    "LINE06": "- Max LLAzShear: 0.002 /s",
                    "LINE07": "- 98% LLAzShear: 0.002 /s",
                    "LINE08": "- 98% MLAzShear: 0.001 /s",
                    "LINE09": "- Norm. vert. growth rate: N/A",
                    "LINE10": "- EBShear: 8.6 kts; SRH 0-1km AGL: 75 m^2/s^2",
                    "LINE11": "- MUCAPE: 403 J/kg; MLCAPE: 297 J/kg; MLCIN: 0 J/kg",
                    "LINE12": "- MeanWind 1-3kmAGL: 22.5 kts",
                    "LINE13": "- Wetbulb 0C hgt: 5.0 kft AGL",
                    "LINE14": "- CAPE -10C to -30C: 94 J/kg; PWAT: 0.8 in.",
                    "LINE15": "Avg. beam height (ARL): 3.48 kft / 1.06 km"
                },
                "probtor": {
                    "PROB": "0",
                    "LINE01": "ProbTor: 0%",
                    "LINE02": "- Max LLAzShear: 0.002 /s (weak)",
                    "LINE03": "- 98% LLAzShear: 0.002 /s (weak)",
                    "LINE04": "- 98% MLAzShear: 0.001 /s (weak)",
                    "LINE05": "- Flash Density: 0.00 fl/min/km^2",
                    "LINE06": "- SRH 0-1km AGL: 75 m2/s2",
                    "LINE07": "- EBShear: 8.6 kts",
                    "LINE08": "- MeanWind 1-3kmAGL: 22.5 kts",
                    "LINE09": "- MLCAPE/MLCIN: 297/0 J/kg",
                    "LINE10": "Avg. beam height (ARL): 3.48 kft / 1.06 km"
                },
                "probhail": {
                    "PROB": "0",
                    "LINE01": "ProbHail: 0%",
                    "LINE02": "- MESH: 0.00 in.",
                    "LINE03": "- Flash Rate: 0 fl/min",
                    "LINE04": "- Norm. vert. growth rate: N/A",
                    "LINE05": "- EBShear: 8.6 kts",
                    "LINE06": "- CAPE -10C to -30C: 94 J/kg",
                    "LINE07": "- PWAT: 0.8 in.",
                    "LINE08": "- Wetbulb 0C hgt: 5.0 kft AGL"
                },
                "probwind": {
                    "PROB": "1",
                    "LINE01": "ProbWind: 1%",
                    "LINE02": "- MESH: 0.00 in.",
                    "LINE03": "- VIL Density: 0.31 g/m^3",
                    "LINE04": "- Flash Rate: 0 fl/min",
                    "LINE05": "- 98% LLAzShear: 0.002 /s (weak)",
                    "LINE06": "- 98% MLAzShear: 0.001 /s (weak)",
                    "LINE07": "- Norm. vert. growth rate: N/A",
                    "LINE08": "- EBShear: 8.6 kts",
                    "LINE09": "- MeanWind 1-3kmAGL: 22.5 kts",
                    "LINE10": "- MUCAPE: 403 J/kg; MLCAPE: 297 J/kg"
                }
            },
            "properties": {
                "MUCAPE": "403",
                "MLCAPE": "297",
                "MLCIN": "0",
                "EBSHEAR": "8.6",
                "SRH01KM": "75",
                "MEANWIND_1-3kmAGL": "22.5",
                "MESH": "0.00",
                "VIL_DENSITY": "0.31",
                "FLASH_RATE": "0",
                "FLASH_DENSITY": "0.00",
                "MAXLLAZ": "0.002",
                "P98LLAZ": "0.002",
                "P98MLAZ": "0.001",
                "MAXRC_EMISS": "N/A",
                "MAXRC_ICECF": "N/A",
                "WETBULB_0C_HGT": "5.0",
                "PWAT": "0.8",
                "CAPE_M10M30": "94",
                "LJA": "0.0",
                "SIZE": "117",
                "AVG_BEAM_HGT": "3.48 kft / 1.06 km",
                "MOTION_EAST": "0.895",
                "MOTION_SOUTH": "-9.521",
                "PS": "0",
                "ID": "128748"
            }
        },
        {
            "type": "Feature",
            "geometry": {
                "type": "Polygon",
                "coordinates": [
                    [
                        [
                            -94.64,
                            43.24
                        ],
                        [
                            -94.62,
                            43.24
                        ],
                        [
                            -94.6,
                            43.2
                        ],
                        [
                            -94.59,
                            43.19
                        ],
                        [
                            -94.57,
                            43.19
                        ],
                        [
                            -94.57,
                            43.16
                        ],
                        [
                            -94.64,
                            43.15
                        ],
                        [
                            -94.65,
                            43.16
                        ],
                        [
                            -94.7,
                            43.17
                        ],
                        [
                            -94.7,
                            43.18
                        ],
                        [
                            -94.68,
                            43.18
                        ],
                        [
                            -94.64,
                            43.22
                        ],
                        [
                            -94.64,
                            43.24
                        ]
                    ]
                ]
            },
            "models": {
                "probsevere": {
                    "PROB": "1",
                    "LINE01": "ProbHail: 0%; ProbWind: 1%; ProbTor: 0%",
                    "LINE02": "- MESH: 0.16 in.",
                    "LINE03": "- VIL Density: 0.73 g/m^3",
                    "LINE04": "- Flash Rate: 0 fl/min",
                    "LINE05": "- Flash Density (max in last 30 min): 0.00 fl/min/km^2",
                    "LINE06": "- Max LLAzShear: 0.002 /s",
                    "LINE07": "- 98% LLAzShear: 0.002 /s",
                    "LINE08": "- 98% MLAzShear: 0.001 /s",
                    "LINE09": "- Norm. vert. growth rate: N/A",
                    "LINE10": "- EBShear: 0.0 kts; SRH 0-1km AGL: 30 m^2/s^2",
                    "LINE11": "- MUCAPE: 0 J/kg; MLCAPE: 0 J/kg; MLCIN: -999 J/kg",
                    "LINE12": "- MeanWind 1-3kmAGL: 12.4 kts",
                    "LINE13": "- Wetbulb 0C hgt: 5.2 kft AGL",
                    "LINE14": "- CAPE -10C to -30C: 0 J/kg; PWAT: 0.4 in.",
                    "LINE15": "Avg. beam height (ARL): 10.52 kft / 3.21 km"
                },
                "probtor": {
                    "PROB": "0",
                    "LINE01": "ProbTor: 0%",
                    "LINE02": "- Max LLAzShear: 0.002 /s (weak)",
                    "LINE03": "- 98% LLAzShear: 0.002 /s (weak)",
                    "LINE04": "- 98% MLAzShear: 0.001 /s (weak)",
                    "LINE05": "- Flash Density: 0.00 fl/min/km^2",
                    "LINE06": "- SRH 0-1km AGL: 30 m2/s2",
                    "LINE07": "- EBShear: 0.0 kts",
                    "LINE08": "- MeanWind 1-3kmAGL: 12.4 kts",
                    "LINE09": "- MLCAPE/MLCIN: 0/-999 J/kg",
                    "LINE10": "Avg. beam height (ARL): 10.52 kft / 3.21 km"
                },
                "probhail": {
                    "PROB": "0",
                    "LINE01": "ProbHail: 0%",
                    "LINE02": "- MESH: 0.16 in.",
                    "LINE03": "- Flash Rate: 0 fl/min",
                    "LINE04": "- Norm. vert. growth rate: N/A",
                    "LINE05": "- EBShear: 0.0 kts",
                    "LINE06": "- CAPE -10C to -30C: 0 J/kg",
                    "LINE07": "- PWAT: 0.4 in.",
                    "LINE08": "- Wetbulb 0C hgt: 5.2 kft AGL"
                },
                "probwind": {
                    "PROB": "1",
                    "LINE01": "ProbWind: 1%",
                    "LINE02": "- MESH: 0.16 in.",
                    "LINE03": "- VIL Density: 0.73 g/m^3",
                    "LINE04": "- Flash Rate: 0 fl/min",
                    "LINE05": "- 98% LLAzShear: 0.002 /s (weak)",
                    "LINE06": "- 98% MLAzShear: 0.001 /s (weak)",
                    "LINE07": "- Norm. vert. growth rate: N/A",
                    "LINE08": "- EBShear: 0.0 kts",
                    "LINE09": "- MeanWind 1-3kmAGL: 12.4 kts",
                    "LINE10": "- MUCAPE: 0 J/kg; MLCAPE: 0 J/kg"
                }
            },
            "properties": {
                "MUCAPE": "0",
                "MLCAPE": "0",
                "MLCIN": "-999",
                "EBSHEAR": "0.0",
                "SRH01KM": "30",
                "MEANWIND_1-3kmAGL": "12.4",
                "MESH": "0.16",
                "VIL_DENSITY": "0.73",
                "FLASH_RATE": "0",
                "FLASH_DENSITY": "0.00",
                "MAXLLAZ": "0.002",
                "P98LLAZ": "0.002",
                "P98MLAZ": "0.001",
                "MAXRC_EMISS": "N/A",
                "MAXRC_ICECF": "N/A",
                "WETBULB_0C_HGT": "5.2",
                "PWAT": "0.4",
                "CAPE_M10M30": "0",
                "LJA": "0.0",
                "SIZE": "77",
                "AVG_BEAM_HGT": "10.52 kft / 3.21 km",
                "MOTION_EAST": "0.895",
                "MOTION_SOUTH": "-9.521",
                "PS": "0",
                "ID": "128749"
            }
        },
        {
            "type": "Feature",
            "geometry": {
                "type": "Polygon",
                "coordinates": [
                    [
                        [
                            -94.01,
                            43.05
                        ],
                        [
                            -93.92,
                            43.05
                        ],
                        [
                            -93.94,
                            43.03
                        ],
                        [
                            -93.94,
                            42.98
                        ],
                        [
                            -93.93,
                            42.97
                        ],
                        [
                            -94.02,
                            42.97
                        ],
                        [
                            -94.01,
                            42.98
                        ],
                        [
                            -94.01,
                            43.05
                        ]
                    ]
                ]
            },
            "models": {
                "probsevere": {
                    "PROB": "1",
                    "LINE01": "ProbHail: 0%; ProbWind: 1%; ProbTor: 0%",
                    "LINE02": "- MESH: 0.18 in.",
                    "LINE03": "- VIL Density: 0.74 g/m^3",
                    "LINE04": "- Flash Rate: 0 fl/min",
                    "LINE05": "- Flash Density (max in last 30 min): 0.00 fl/min/km^2",
                    "LINE06": "- Max LLAzShear: 0.000 /s",
                    "LINE07": "- 98% LLAzShear: 0.000 /s",
                    "LINE08": "- 98% MLAzShear: 0.000 /s",
                    "LINE09": "- Norm. vert. growth rate: N/A",
                    "LINE10": "- EBShear: 0.0 kts; SRH 0-1km AGL: 23 m^2/s^2",
                    "LINE11": "- MUCAPE: 0 J/kg; MLCAPE: 0 J/kg; MLCIN: -999 J/kg",
                    "LINE12": "- MeanWind 1-3kmAGL: 12.8 kts",
                    "LINE13": "- Wetbulb 0C hgt: 4.7 kft AGL",
                    "LINE14": "- CAPE -10C to -30C: 0 J/kg; PWAT: 0.4 in.",
                    "LINE15": "Avg. beam height (ARL): 6.89 kft / 2.10 km"
                },
                "probtor": {
                    "PROB": "0",
                    "LINE01": "ProbTor: 0%",
                    "LINE02": "- Max LLAzShear: 0.000 /s (weak)",
                    "LINE03": "- 98% LLAzShear: 0.000 /s (weak)",
                    "LINE04": "- 98% MLAzShear: 0.000 /s (weak)",
                    "LINE05": "- Flash Density: 0.00 fl/min/km^2",
                    "LINE06": "- SRH 0-1km AGL: 23 m2/s2",
                    "LINE07": "- EBShear: 0.0 kts",
                    "LINE08": "- MeanWind 1-3kmAGL: 12.8 kts",
                    "LINE09": "- MLCAPE/MLCIN: 0/-999 J/kg",
                    "LINE10": "Avg. beam height (ARL): 6.89 kft / 2.10 km"
                },
                "probhail": {
                    "PROB": "0",
                    "LINE01": "ProbHail: 0%",
                    "LINE02": "- MESH: 0.18 in.",
                    "LINE03": "- Flash Rate: 0 fl/min",
                    "LINE04": "- Norm. vert. growth rate: N/A",
                    "LINE05": "- EBShear: 0.0 kts",
                    "LINE06": "- CAPE -10C to -30C: 0 J/kg",
                    "LINE07": "- PWAT: 0.4 in.",
                    "LINE08": "- Wetbulb 0C hgt: 4.7 kft AGL"
                },
                "probwind": {
                    "PROB": "1",
                    "LINE01": "ProbWind: 1%",
                    "LINE02": "- MESH: 0.18 in.",
                    "LINE03": "- VIL Density: 0.74 g/m^3",
                    "LINE04": "- Flash Rate: 0 fl/min",
                    "LINE05": "- 98% LLAzShear: 0.000 /s (weak)",
                    "LINE06": "- 98% MLAzShear: 0.000 /s (weak)",
                    "LINE07": "- Norm. vert. growth rate: N/A",
                    "LINE08": "- EBShear: 0.0 kts",
                    "LINE09": "- MeanWind 1-3kmAGL: 12.8 kts",
                    "LINE10": "- MUCAPE: 0 J/kg; MLCAPE: 0 J/kg"
                }
            },
            "properties": {
                "MUCAPE": "0",
                "MLCAPE": "0",
                "MLCIN": "-999",
                "EBSHEAR": "0.0",
                "SRH01KM": "23",
                "MEANWIND_1-3kmAGL": "12.8",
                "MESH": "0.18",
                "VIL_DENSITY": "0.74",
                "FLASH_RATE": "0",
                "FLASH_DENSITY": "0.00",
                "MAXLLAZ": "0.000",
                "P98LLAZ": "0.000",
                "P98MLAZ": "0.000",
                "MAXRC_EMISS": "N/A",
                "MAXRC_ICECF": "N/A",
                "WETBULB_0C_HGT": "4.7",
                "PWAT": "0.4",
                "CAPE_M10M30": "0",
                "LJA": "0.0",
                "SIZE": "77",
                "AVG_BEAM_HGT": "6.89 kft / 2.10 km",
                "MOTION_EAST": "0.895",
                "MOTION_SOUTH": "-9.521",
                "PS": "0",
                "ID": "128750"
            }
        },
        {
            "type": "Feature",
            "geometry": {
                "type": "Polygon",
                "coordinates": [
                    [
                        [
                            -95.35,
                            38.04
                        ],
                        [
                            -95.35,
                            38.03
                        ],
                        [
                            -95.33,
                            38.02
                        ],
                        [
                            -95.32,
                            37.99
                        ],
                        [
                            -95.33,
                            37.98
                        ],
                        [
                            -95.33,
                            37.95
                        ],
                        [
                            -95.36,
                            37.93
                        ],
                        [
                            -95.37,
                            37.97
                        ],
                        [
                            -95.38,
                            37.98
                        ],
                        [
                            -95.38,
                            38.01
                        ],
                        [
                            -95.36,
                            38.02
                        ],
                        [
                            -95.35,
                            38.04
                        ]
                    ]
                ]
            },
            "models": {
                "probsevere": {
                    "PROB": "1",
                    "LINE01": "ProbHail: 0%; ProbWind: 1%; ProbTor: 0%",
                    "LINE02": "- MESH: 0.09 in.",
                    "LINE03": "- VIL Density: 0.75 g/m^3",
                    "LINE04": "- Flash Rate: 0 fl/min",
                    "LINE05": "- Flash Density (max in last 30 min): 0.00 fl/min/km^2",
                    "LINE06": "- Max LLAzShear: 0.000 /s",
                    "LINE07": "- 98% LLAzShear: 0.000 /s",
                    "LINE08": "- 98% MLAzShear: 0.000 /s",
                    "LINE09": "- Norm. vert. growth rate: N/A",
                    "LINE10": "- EBShear: 0.0 kts; SRH 0-1km AGL: 53 m^2/s^2",
                    "LINE11": "- MUCAPE: 0 J/kg; MLCAPE: 0 J/kg; MLCIN: -999 J/kg",
                    "LINE12": "- MeanWind 1-3kmAGL: 9.5 kts",
                    "LINE13": "- Wetbulb 0C hgt: 7.5 kft AGL",
                    "LINE14": "- CAPE -10C to -30C: 0 J/kg; PWAT: 0.5 in.",
                    "LINE15": "Avg. beam height (ARL): 7.16 kft / 2.18 km"
                },
                "probtor": {
                    "PROB": "0",
                    "LINE01": "ProbTor: 0%",
                    "LINE02": "- Max LLAzShear: 0.000 /s (weak)",
                    "LINE03": "- 98% LLAzShear: 0.000 /s (weak)",
                    "LINE04": "- 98% MLAzShear: 0.000 /s (weak)",
                    "LINE05": "- Flash Density: 0.00 fl/min/km^2",
                    "LINE06": "- SRH 0-1km AGL: 53 m2/s2",
                    "LINE07": "- EBShear: 0.0 kts",
                    "LINE08": "- MeanWind 1-3kmAGL: 9.5 kts",
                    "LINE09": "- MLCAPE/MLCIN: 0/-999 J/kg",
                    "LINE10": "Avg. beam height (ARL): 7.16 kft / 2.18 km"
                },
                "probhail": {
                    "PROB": "0",
                    "LINE01": "ProbHail: 0%",
                    "LINE02": "- MESH: 0.09 in.",
                    "LINE03": "- Flash Rate: 0 fl/min",
                    "LINE04": "- Norm. vert. growth rate: N/A",
                    "LINE05": "- EBShear: 0.0 kts",
                    "LINE06": "- CAPE -10C to -30C: 0 J/kg",
                    "LINE07": "- PWAT: 0.5 in.",
                    "LINE08": "- Wetbulb 0C hgt: 7.5 kft AGL"
                },
                "probwind": {
                    "PROB": "1",
                    "LINE01": "ProbWind: 1%",
                    "LINE02": "- MESH: 0.09 in.",
                    "LINE03": "- VIL Density: 0.75 g/m^3",
                    "LINE04": "- Flash Rate: 0 fl/min",
                    "LINE05": "- 98% LLAzShear: 0.000 /s (weak)",
                    "LINE06": "- 98% MLAzShear: 0.000 /s (weak)",
                    "LINE07": "- Norm. vert. growth rate: N/A",
                    "LINE08": "- EBShear: 0.0 kts",
                    "LINE09": "- MeanWind 1-3kmAGL: 9.5 kts",
                    "LINE10": "- MUCAPE: 0 J/kg; MLCAPE: 0 J/kg"
                }
            },
            "properties": {
                "MUCAPE": "0",
                "MLCAPE": "0",
                "MLCIN": "-999",
                "EBSHEAR": "0.0",
                "SRH01KM": "53",
                "MEANWIND_1-3kmAGL": "9.5",
                "MESH": "0.09",
                "VIL_DENSITY": "0.75",
                "FLASH_RATE": "0",
                "FLASH_DENSITY": "0.00",
                "MAXLLAZ": "0.000",
                "P98LLAZ": "0.000",
                "P98MLAZ": "0.000",
                "MAXRC_EMISS": "N/A",
                "MAXRC_ICECF": "N/A",
                "WETBULB_0C_HGT": "7.5",
                "PWAT": "0.5",
                "CAPE_M10M30": "0",
                "LJA": "0.0",
                "SIZE": "52",
                "AVG_BEAM_HGT": "7.16 kft / 2.18 km",
                "MOTION_EAST": "0.895",
                "MOTION_SOUTH": "-9.521",
                "PS": "0",
                "ID": "128751"
            }
        },
        {
            "type": "Feature",
            "geometry": {
                "type": "Polygon",
                "coordinates": [
                    [
                        [
                            -101.4,
                            36.38
                        ],
                        [
                            -101.36,
                            36.38
                        ],
                        [
                            -101.36,
                            36.35
                        ],
                        [
                            -101.38,
                            36.32
                        ],
                        [
                            -101.41,
                            36.32
                        ],
                        [
                            -101.43,
                            36.34
                        ],
                        [
                            -101.44,
                            36.34
                        ],
                        [
                            -101.42,
                            36.35
                        ],
                        [
                            -101.4,
                            36.37
                        ],
                        [
                            -101.4,
                            36.38
                        ]
                    ]
                ]
            },
            "models": {
                "probsevere": {
                    "PROB": "1",
                    "LINE01": "ProbHail: 0%; ProbWind: 1%; ProbTor: 0%",
                    "LINE02": "- MESH: 0.27 in.",
                    "LINE03": "- VIL Density: 0.85 g/m^3",
                    "LINE04": "- Flash Rate: 0 fl/min",
                    "LINE05": "- Flash Density (max in last 30 min): 0.00 fl/min/km^2",
                    "LINE06": "- Max LLAzShear: 0.003 /s",
                    "LINE07": "- 98% LLAzShear: 0.002 /s",
                    "LINE08": "- 98% MLAzShear: 0.002 /s",
                    "LINE09": "- Norm. vert. growth rate: N/A",
                    "LINE10": "- EBShear: 0.0 kts; SRH 0-1km AGL: 15 m^2/s^2",
                    "LINE11": "- MUCAPE: 0 J/kg; MLCAPE: 0 J/kg; MLCIN: -999 J/kg",
                    "LINE12": "- MeanWind 1-3kmAGL: 14.0 kts",
                    "LINE13": "- Wetbulb 0C hgt: 6.3 kft AGL",
                    "LINE14": "- CAPE -10C to -30C: 0 J/kg; PWAT: 0.3 in.",
                    "LINE15": "Avg. beam height (ARL): 5.77 kft / 1.76 km"
                },
                "probtor": {
                    "PROB": "0",
                    "LINE01": "ProbTor: 0%",
                    "LINE02": "- Max LLAzShear: 0.003 /s (weak)",
                    "LINE03": "- 98% LLAzShear: 0.002 /s (weak)",
                    "LINE04": "- 98% MLAzShear: 0.002 /s (weak)",
                    "LINE05": "- Flash Density: 0.00 fl/min/km^2",
                    "LINE06": "- SRH 0-1km AGL: 15 m2/s2",
                    "LINE07": "- EBShear: 0.0 kts",
                    "LINE08": "- MeanWind 1-3kmAGL: 14.0 kts",
                    "LINE09": "- MLCAPE/MLCIN: 0/-999 J/kg",
                    "LINE10": "Avg. beam height (ARL): 5.77 kft / 1.76 km"
                },
                "probhail": {
                    "PROB": "0",
                    "LINE01": "ProbHail: 0%",
                    "LINE02": "- MESH: 0.27 in.",
                    "LINE03": "- Flash Rate: 0 fl/min",
                    "LINE04": "- Norm. vert. growth rate: N/A",
                    "LINE05": "- EBShear: 0.0 kts",
                    "LINE06": "- CAPE -10C to -30C: 0 J/kg",
                    "LINE07": "- PWAT: 0.3 in.",
                    "LINE08": "- Wetbulb 0C hgt: 6.3 kft AGL"
                },
                "probwind": {
                    "PROB": "1",
                    "LINE01": "ProbWind: 1%",
                    "LINE02": "- MESH: 0.27 in.",
                    "LINE03": "- VIL Density: 0.85 g/m^3",
                    "LINE04": "- Flash Rate: 0 fl/min",
                    "LINE05": "- 98% LLAzShear: 0.002 /s (weak)",
                    "LINE06": "- 98% MLAzShear: 0.002 /s (weak)",
                    "LINE07": "- Norm. vert. growth rate: N/A",
                    "LINE08": "- EBShear: 0.0 kts",
                    "LINE09": "- MeanWind 1-3kmAGL: 14.0 kts",
                    "LINE10": "- MUCAPE: 0 J/kg; MLCAPE: 0 J/kg"
                }
            },
            "properties": {
                "MUCAPE": "0",
                "MLCAPE": "0",
                "MLCIN": "-999",
                "EBSHEAR": "0.0",
                "SRH01KM": "15",
                "MEANWIND_1-3kmAGL": "14.0",
                "MESH": "0.27",
                "VIL_DENSITY": "0.85",
                "FLASH_RATE": "0",
                "FLASH_DENSITY": "0.00",
                "MAXLLAZ": "0.003",
                "P98LLAZ": "0.002",
                "P98MLAZ": "0.002",
                "MAXRC_EMISS": "N/A",
                "MAXRC_ICECF": "N/A",
                "WETBULB_0C_HGT": "6.3",
                "PWAT": "0.3",
                "CAPE_M10M30": "0",
                "LJA": "0.0",
                "SIZE": "42",
                "AVG_BEAM_HGT": "5.77 kft / 1.76 km",
                "MOTION_EAST": "0.895",
                "MOTION_SOUTH": "-9.521",
                "PS": "0",
                "ID": "128752"
            }
        }
    ]
}